{
	"fileName": "20130222JRL110R2.xlsx",
	"savedJsonName": "C:\\Dropbox\\Proj_fullstack\\proj_excel\\2013\\20130222JRL110R2.json",
	"score": 722,
	"title": "SGM-SPBS 设备停机报告",
	"codeNo": "",
	"downtimeDate": "2013年2月22日16时30分",
	"fileNameDate": "20130222",
	"equipName": "设备名称:机器人焊枪",
	"breakdownTime": "停机时间：15min",
	"areaLocation": "停机区域\/点:JRL",
	"maintainTeam": "维修班组：C",
	"lostTime": "15",
	"lostProductNum": "12",
	"plantName": "厂区：SPBS\nPlant",
	"originator": "填表人\/日期   黄波       \nOringinator ",
	"troubleShooting": [
		[
			{
				"step": 1,
				"descr": "生产过程中机器人焊枪无法关闭大行程；",
				"lostMin": "",
				"success": "O"
			}
		],
		[
			{
				"step": 2,
				"descr": "用示教板操作机器人焊枪关闭，发现电磁阀没有信号电压；",
				"lostMin": "",
				"success": "O"
			}
		],
		[
			{
				"step": 3,
				"descr": "怀疑焊枪控制线路断路，检查相关接插件外观未发现异常；",
				"lostMin": "",
				"success": "O"
			}
		],
		[
			{
				"step": 4,
				"descr": "怀疑焊枪控制19芯电缆有问题，立即与生产联系后准备BACKUP补焊的预案；",
				"lostMin": "",
				"success": "O"
			}
		],
		[
			{
				"step": 5,
				"descr": "用备件19芯电缆飞线捆扎到机器人DRESS套管外部；",
				"lostMin": "",
				"success": "O"
			}
		],
		[
			{
				"step": 6,
				"descr": "试焊确认焊枪功能正常，调整电缆捆扎位置并检查2种机器人轨迹后恢复设备正常运行；",
				"lostMin": "",
				"success": "O"
			}
		],
		[
			{
				"step": 7,
				"descr": "",
				"lostMin": "",
				"success": ""
			}
		]
	],
	"faultDescription": [
		[
			"生产过程中JRL110R2焊枪无法关闭大行程"
		],
		[
			""
		],
		[
			""
		],
		[
			""
		],
		[
			""
		],
		[
			""
		]
	],
	"fiveWhy": [
		[
			"为什么机器人焊枪无法闭合？因为焊枪关枪电磁阀没有动作；"
		],
		[
			"为什么焊枪关枪电磁阀没有动作？因为关枪电磁阀没有DC24V控制电压；"
		],
		[
			"为什么关枪电磁阀没有DC24V控制电压？因为焊枪19芯控制电缆内部断路；"
		],
		[
			"为什么焊枪19芯控制电缆内部断路？因为19芯信号电缆在Dress外露部分预留长度不够，导致线缆受到拉扯力后内部导线断路；"
		],
		[
			""
		]
	],
	"rootCause": "因为19芯信号电缆在Dress外露部分预留长度不够，导致线缆受到拉扯力后内部导线断路；    ",
	"shortTerm": [
		[
			{
				"counterMeasure": "用备件19芯电缆飞线恢复机器人焊枪正常功能",
				"resp": "袁炜",
				"supp": "程超",
				"compDate": "2\/22\/2013",
				"status": "4\/4"
			}
		],
		[
			{
				"counterMeasure": "",
				"resp": "",
				"supp": "",
				"compDate": "",
				"status": ""
			}
		],
		[
			{
				"counterMeasure": "",
				"resp": "",
				"supp": "",
				"compDate": "",
				"status": ""
			}
		]
	],
	"longTerm": [
		[
			{
				"counterMeasure": "1.非生产日拆卸接插件或拆下电缆检查确切原因，根据确切断路原因实施长期整改措施。",
				"resp": "黄光耀",
				"supp": "",
				"compDate": "2\/25\/2013",
				"status": "2\/4"
			}
		],
		[
			{
				"counterMeasure": "2.更换Dress J6出口出的橡胶线夹，防止19芯线缆受到拉力后窜动。",
				"resp": "黄光耀",
				"supp": "",
				"compDate": "2\/24\/2013",
				"status": "2\/4"
			}
		],
		[
			{
				"counterMeasure": "",
				"resp": "",
				"supp": "",
				"compDate": "",
				"status": ""
			}
		],
		[
			{
				"counterMeasure": "",
				"resp": "",
				"supp": "",
				"compDate": "",
				"status": ""
			}
		]
	],
	"correctPath": [
		[
			{
				"step": "",
				"descr": "同维修处理过程"
			}
		],
		[
			{
				"step": "",
				"descr": ""
			}
		],
		[
			{
				"step": "",
				"descr": ""
			}
		],
		[
			{
				"step": "",
				"descr": ""
			}
		],
		[
			{
				"step": "",
				"descr": ""
			}
		],
		[
			{
				"step": "",
				"descr": ""
			}
		]
	],
	"person_TL": "班组长\/TL:曹鸣晓",
	"person_ENG": "工程师\/ENG.:程超",
	"person_GL": "工段长\/ GL:黄波",
	"person_Manager": "技术经理\/Tech.Manager.:邱正东"
}
